setup.py
Flask_MakoTemplates.egg-info/PKG-INFO
Flask_MakoTemplates.egg-info/SOURCES.txt
Flask_MakoTemplates.egg-info/dependency_links.txt
Flask_MakoTemplates.egg-info/namespace_packages.txt
Flask_MakoTemplates.egg-info/not-zip-safe
Flask_MakoTemplates.egg-info/requires.txt
Flask_MakoTemplates.egg-info/top_level.txt
flaskext/__init__.py
flaskext/makotemplates.py