Metadata-Version: 1.0
Name: Flask-MakoTemplates
Version: 0.2
Summary: Mako templates support for Flask applications.
Home-page: https://github.com/benselme/flask-makotemplates
Author: Beranger Enselme
Author-email: benselme@gmail.com
License: BSD
Platform: any
Classifier: Development Status :: 3 - Alpha
Classifier: Environment :: Web Environment
Classifier: Intended Audience :: Developers
Classifier: License :: OSI Approved :: BSD License
Classifier: Operating System :: OS Independent
Classifier: Programming Language :: Python
Classifier: Topic :: Internet :: WWW/HTTP :: Dynamic Content
Classifier: Topic :: Software Development :: Libraries :: Python Modules
